tabsus/__init__.py
tabsus/dataframe.py
tabsus/file_loader.py
tabsus/parse_helper.py
tabsus/wrapper.py
tabsus/conversion/__init__.py
tabsus/conversion/dbf.py
tabsus/conversion/loader.py
tabsus/conversion/cnv/__init__.py
tabsus/conversion/cnv/lookup.py
tabsus/conversion/cnv/parser.py
tabsus/definition/__init__.py
tabsus/definition/access.py
tabsus/definition/parser.py
tabsus-0.0.1.dist-info/LICENSE
tabsus-0.0.1.dist-info/METADATA
tabsus-0.0.1.dist-info/WHEEL
tabsus-0.0.1.dist-info/top_level.txt
tabsus-0.0.1.dist-info/RECORD
