Metadata-Version: 2.1
Name: tabsus
Version: 0.0.1
Summary: Library for processing DATASUS database files
Home-page: https://github.com/gcms/tabsus
Author: Gustavo Sousa
Author-email: gustavocms@acm.org
License: UNKNOWN
Project-URL: Source Code, https://github.com/gcms/tabsus
Platform: UNKNOWN
Classifier: Programming Language :: Python :: 3
Classifier: License :: OSI Approved :: MIT License
Classifier: Operating System :: OS Independent
Requires-Python: >=3.6
License-File: LICENSE
Requires-Dist: intervaltree (>=3.1.0)
Requires-Dist: nocasedict (>=1.0.2)
Requires-Dist: dbfread (==2.0.7)
Requires-Dist: pandas (>=1.2.3)
Provides-Extra: test
